odoo/addons/sms_messagebird/README.rst
odoo/addons/sms_messagebird/__init__.py
odoo/addons/sms_messagebird/__manifest__.py
odoo/addons/sms_messagebird/i18n/sms_messagebird.pot
odoo/addons/sms_messagebird/models/__init__.py
odoo/addons/sms_messagebird/models/ir_sms_gateway.py
odoo/addons/sms_messagebird/readme/CONFIGURE.md
odoo/addons/sms_messagebird/readme/CONTRIBUTORS.md
odoo/addons/sms_messagebird/readme/DESCRIPTION.md
odoo/addons/sms_messagebird/static/description/icon.png
odoo/addons/sms_messagebird/static/description/index.html
odoo/addons/sms_messagebird/tests/__init__.py
odoo/addons/sms_messagebird/tests/test_sms_messagebird.py
odoo/addons/sms_messagebird/views/ir_sms_gateway.xml
odoo_addon_sms_messagebird-16.0.1.0.0.2.dist-info/METADATA
odoo_addon_sms_messagebird-16.0.1.0.0.2.dist-info/WHEEL
odoo_addon_sms_messagebird-16.0.1.0.0.2.dist-info/top_level.txt
odoo_addon_sms_messagebird-16.0.1.0.0.2.dist-info/RECORD
